LICENSE
MANIFEST.in
README.md
setup.cfg
setup.py
versioneer.py
tests/api/__init__.py
tests/api/constants.py
tests/api/payloads.py
tests/api/test_apis.py
tests/api/test_bulk.py
tests/api/test_exceptions.py
tests/api/test_plural_lists.py
tests/api/test_queryset.py
tests/api/test_relationships.py
tests/api/test_single_resource.py
tests/common/__init__.py
tests/common/test_is_plural.py
tests/common/test_strings.py
tests/native/__init__.py
tests/native/conftest.py
tests/native/core/__init__.py
tests/native/core/test_cache.py
tests/native/core/test_cds.py
tests/native/core/test_core.py
tests/native/core/test_daemon.py
tests/native/core/test_init.py
tests/native/core/test_parsing.py
tests/native/core/test_rendering.py
tests/native/core/test_tools/__init__.py
tests/native/core/test_tools/test_migrations/__init__.py
tests/native/core/test_tools/test_migrations/test_mark.py
tests/native/core/test_tools/test_migrations/test_models.py
tests/native/core/test_tools/test_migrations/test_review.py
tests/native/core/test_tools/test_migrations/test_save.py
tests/native/django/__init__.py
tests/native/django/settings.py
tests/native/django/test_templatetag.py
tests/native/django/test_commands/__init__.py
tests/native/django/test_commands/test_invalidatetransifex.py
tests/native/django/test_commands/test_migratetransifex.py
tests/native/django/test_commands/test_pushtransifex.py
tests/native/django/test_tools/__init__.py
tests/native/django/test_tools/test_migrations/__init__.py
tests/native/django/test_tools/test_migrations/test_templatetags.py
tests/native/django/test_utils/__init__.py
tests/native/django/test_utils/test_init.py
tests/native/django/test_utils/test_templates.py
transifex/__init__.py
transifex/_version.py
transifex/api/__init__.py
transifex/api/exceptions.py
transifex/api/jsonapi/__init__.py
transifex/api/jsonapi/apis.py
transifex/api/jsonapi/auth.py
transifex/api/jsonapi/collections.py
transifex/api/jsonapi/compat.py
transifex/api/jsonapi/exceptions.py
transifex_python.egg-info/PKG-INFO
transifex_python.egg-info/SOURCES.txt
transifex_python.egg-info/dependency_links.txt
transifex_python.egg-info/requires.txt
transifex_python.egg-info/top_level.txt