Metadata-Version: 2.4
Name: transifex-python
Version: 3.7.0
Summary: Transifex Python Toolkit
Home-page: https://github.com/transifex/transifex-python
Author: Transifex
Author-email: info@transifex.com
Classifier: Programming Language :: Python :: 3.6
Classifier: License :: OSI Approved :: Apache Software License
Classifier: Operating System :: OS Independent
License-File: LICENSE
Requires-Dist: pyseeyou
Requires-Dist: requests
Requires-Dist: click
Requires-Dist: asttokens
Dynamic: author
Dynamic: author-email
Dynamic: classifier
Dynamic: description
Dynamic: description-content-type
Dynamic: home-page
Dynamic: license-file
Dynamic: requires-dist
Dynamic: summary
